quantex/__init__.py
quantex/backtester.py
quantex/broker.py
quantex/datasource.py
quantex/enums.py
quantex/helpers.py
quantex/strategy.py
quantex-0.2.6.dist-info/LICENSE.md
quantex-0.2.6.dist-info/METADATA
quantex-0.2.6.dist-info/WHEEL
quantex-0.2.6.dist-info/RECORD
