Metadata-Version: 2.3
Name: quantex
Version: 0.2.6
Summary: A simple quant strategy creation and backtesting package.
License: MIT
Author: Daniel Green
Author-email: dangreen07@outlook.com
Requires-Python: >=3.10,<4
Classifier: License :: OSI Approved :: MIT License
Classifier: Programming Language :: Python :: 3
Classifier: Programming Language :: Python :: 3.10
Classifier: Programming Language :: Python :: 3.11
Classifier: Programming Language :: Python :: 3.12
Classifier: Programming Language :: Python :: 3.13
Requires-Dist: fastparquet (>=2024.11.0,<2025.0.0)
Requires-Dist: pandas (>=2.3.0,<3.0.0)
Requires-Dist: pyarrow (>=20.0.0,<21.0.0)
Requires-Dist: tqdm (>=4.67.1,<5.0.0)
